{
  "effects": {
    "sky_color": 12632319,
    "foliage_color": 14483329,
    "grass_color": 11665355,
    "fog_color": 16777215,
    "water_color": 5826047,
    "water_fog_color": 5826047,
    "music": {
      "sound": "the_aether:above",
      "min_delay": 280,
      "max_delay": 14400,
      "replace_current_music": true
    }
  },
  "surface_builder": "the_aether:aether_surface_builder",
  "carvers": {},
  "features": [],
  "starts": [],
  "spawners": {
    "monster": [
      {
        "type": "the_aether:blue_swet",
        "weight": 100,
        "minCount": 2,
        "maxCount": 6
      }
    ],
    "creature": [
      {
        "type": "the_aether:aerbunny",
        "weight": 12,
        "minCount": 4,
        "maxCount": 4
      },
      {
        "type": "the_aether:moa",
        "weight": 6,
        "minCount": 1,
        "maxCount": 3
      },
      {
        "type": "the_aether:aerwhale",
        "weight": 6,
        "minCount": 1,
        "maxCount": 3
      }
    ],
    "water_creature": [],
    "water_ambient": [],
    "misc": []
  },
  "spawn_costs": {
      "the_aether:blue_swet": {
      "energy_budget": 0.12,
      "charge": 1.0
    }
  },
  "player_spawn_friendly": false,
  "precipitation": "rain",
  "temperature": 0.5,
  "downfall": 1.0,
  "category": "plains",
  "depth": 0.1,
  "scale": 0.1
}